helloworld_123_test.py
helloworld_123_test-0.0.1.dist-info/METADATA
helloworld_123_test-0.0.1.dist-info/WHEEL
helloworld_123_test-0.0.1.dist-info/top_level.txt
helloworld_123_test-0.0.1.dist-info/RECORD
