Metadata-Version: 2.1
Name: helloworld-123-test
Version: 0.0.1
Summary: Say hello
Home-page: https://github.com/daisydiwang/helloworld_123_test
Author: Di Wang
Author-email: di-wang@uiowa.edu
Keywords: 3D brain image,statistics,hierarchical structure
Classifier: Intended Audience :: Science/Research
Classifier: Programming Language :: Python :: 3
Classifier: License :: OSI Approved :: Apache Software License
Classifier: Operating System :: OS Independent
Requires-Python: >=3.6
Requires-Dist: numpy
Requires-Dist: pandas
